<?xml version="1.0" encoding="UTF-8"?>
<!DOCTYPE plist PUBLIC "-//Apple//DTD PLIST 1.0//EN" "http://www.apple.com/DTDs/PropertyList-1.0.dtd"/>

<plist version="1.0">
    <dict>
        <key>ROOT</key>
        <array>
            <dict>
                <key>id</key>
                <string>115</string>
                <key>children</key>
                <array>
                    <string>1923</string>
                    <string>1925</string>
                    <string>1927</string>
                    <string>1931</string>
                    <string>1933</string>
                    <string>1936</string>
                    <string>2056</string>
                    <string>2085</string>
                    <string>2380</string>
                    <string>2447</string>
                    <string>2449</string>
                    <string>2451</string>
                    <string>2453</string>
                    <string>2835</string>
                    <string>2841</string>
                    <string>3792</string>
                    <string>3794</string>
                    <string>3796</string>
                    <string>3826</string>
                    <string>5474</string>
                    <string>5478</string>
                    <string>5482</string>
                </array>
                <key>childLinkers</key>
                <array>
                    <string>3782</string>
                    <string>3783</string>
                    <string>3784</string>
                    <string>3785</string>
                    <string>3786</string>
                    <string>3787</string>
                    <string>3788</string>
                    <string>3789</string>
                    <string>3790</string>
                    <string>3861</string>
                </array>
            </dict>
            <dict>
                <key>id</key>
                <string>3181</string>
                <key>children</key>
                <array>
                    <string>3622</string>
                    <string>4759</string>
                    <string>4761</string>
                    <string>4763</string>
                    <string>4765</string>
                    <string>4767</string>
                    <string>4769</string>
                    <string>4771</string>
                    <string>4773</string>
                    <string>4775</string>
                    <string>4777</string>
                    <string>4779</string>
                    <string>4781</string>
                    <string>5058</string>
                    <string>5061</string>
                    <string>5063</string>
                    <string>5065</string>
                    <string>5070</string>
                    <string>5076</string>
                    <string>5082</string>
                    <string>5179</string>
                    <string>5588</string>
                    <string>5590</string>
                    <string>5592</string>
                    <string>5594</string>
                    <string>5596</string>
                    <string>5598</string>
                    <string>5600</string>
                    <string>5602</string>
                </array>
                <key>childLinkers</key>
                <array>
                    <string>5181</string>
                </array>
            </dict>
            <dict>
                <key>id</key>
                <string>116</string>
                <key>children</key>
                <array>
                    <string>2124</string>
                    <string>2126</string>
                    <string>2147</string>
                    <string>2463</string>
                    <string>2474</string>
                    <string>2480</string>
                    <string>2493</string>
                    <string>2495</string>
                    <string>2497</string>
                    <string>2533</string>
                    <string>2535</string>
                    <string>2537</string>
                    <string>2539</string>
                    <string>2541</string>
                    <string>3864</string>
                    <string>3866</string>
                    <string>3868</string>
                    <string>3870</string>
                    <string>3872</string>
                    <string>4269</string>
                    <string>4311</string>
                    <string>4322</string>
                    <string>4333</string>
                    <string>4339</string>
                    <string>4345</string>
                    <string>4351</string>
                    <string>4357</string>
                    <string>4363</string>
                    <string>4369</string>
                    <string>4375</string>
                    <string>4381</string>
                    <string>4387</string>
                    <string>4393</string>
                    <string>4399</string>
                    <string>4405</string>
                    <string>4411</string>
                    <string>4417</string>
                    <string>4423</string>
                    <string>4429</string>
                    <string>4435</string>
                    <string>5488</string>
                    <string>5492</string>
                    <string>5496</string>
                    <string>5500</string>
                </array>
                <key>childLinkers</key>
                <array>
                    <string>2543</string>
                    <string>2544</string>
                    <string>2545</string>
                    <string>3797</string>
                    <string>3798</string>
                    <string>3799</string>
                    <string>3800</string>
                    <string>3801</string>
                    <string>3802</string>
                </array>
            </dict>
            <dict>
                <key>id</key>
                <string>3182</string>
                <key>children</key>
                <array>
                    <string>4799</string>
                    <string>4801</string>
                    <string>4803</string>
                    <string>4805</string>
                    <string>4807</string>
                    <string>4809</string>
                    <string>4811</string>
                    <string>4813</string>
                    <string>4815</string>
                    <string>4817</string>
                    <string>4819</string>
                    <string>4821</string>
                    <string>5097</string>
                    <string>5114</string>
                    <string>5118</string>
                    <string>5605</string>
                    <string>5607</string>
                    <string>5609</string>
                </array>
                <key>childLinkers</key>
                <array/>
            </dict>
            <dict>
                <key>id</key>
                <string>808</string>
                <key>children</key>
                <array>
                    <string>2609</string>
                    <string>2611</string>
                    <string>2613</string>
                    <string>2615</string>
                    <string>2617</string>
                    <string>2620</string>
                    <string>2622</string>
                    <string>2624</string>
                    <string>2633</string>
                    <string>2639</string>
                    <string>4456</string>
                    <string>4462</string>
                    <string>4468</string>
                    <string>4474</string>
                    <string>4480</string>
                    <string>4486</string>
                    <string>4492</string>
                    <string>4498</string>
                    <string>4504</string>
                    <string>4510</string>
                    <string>4516</string>
                    <string>4522</string>
                    <string>4528</string>
                    <string>4534</string>
                    <string>4540</string>
                    <string>4546</string>
                    <string>4552</string>
                    <string>4558</string>
                    <string>4564</string>
                    <string>4570</string>
                    <string>5378</string>
                    <string>5380</string>
                    <string>5506</string>
                    <string>5510</string>
                    <string>5514</string>
                </array>
                <key>childLinkers</key>
                <array>
                    <string>3804</string>
                    <string>3805</string>
                    <string>3806</string>
                    <string>3807</string>
                    <string>3808</string>
                    <string>3809</string>
                </array>
            </dict>
            <dict>
                <key>id</key>
                <string>3183</string>
                <key>children</key>
                <array>
                    <string>4838</string>
                    <string>4840</string>
                    <string>4850</string>
                    <string>4852</string>
                    <string>4854</string>
                    <string>4856</string>
                    <string>4858</string>
                    <string>5166</string>
                    <string>5168</string>
                    <string>5170</string>
                    <string>5172</string>
                    <string>5174</string>
                    <string>5190</string>
                    <string>5196</string>
                    <string>5202</string>
                    <string>5208</string>
                    <string>5214</string>
                    <string>5220</string>
                    <string>5226</string>
                    <string>5232</string>
                    <string>5238</string>
                    <string>5244</string>
                    <string>5250</string>
                    <string>5256</string>
                    <string>5262</string>
                    <string>5268</string>
                    <string>5274</string>
                    <string>5612</string>
                    <string>5614</string>
                    <string>5616</string>
                    <string>5618</string>
                    <string>5620</string>
                    <string>5622</string>
                </array>
                <key>childLinkers</key>
                <array/>
            </dict>
            <dict>
                <key>id</key>
                <string>2753</string>
                <key>children</key>
                <array>
                    <string>2756</string>
                    <string>2758</string>
                    <string>2760</string>
                    <string>2762</string>
                    <string>2764</string>
                    <string>2766</string>
                    <string>2768</string>
                    <string>2770</string>
                    <string>2772</string>
                    <string>2783</string>
                    <string>2788</string>
                    <string>2794</string>
                    <string>5383</string>
                    <string>5385</string>
                    <string>5387</string>
                    <string>5389</string>
                    <string>5391</string>
                </array>
                <key>childLinkers</key>
                <array>
                    <string>3812</string>
                    <string>3813</string>
                    <string>3814</string>
                    <string>3815</string>
                    <string>3816</string>
                    <string>3817</string>
                    <string>3818</string>
                    <string>3819</string>
                </array>
            </dict>
            <dict>
                <key>id</key>
                <string>3184</string>
                <key>children</key>
                <array>
                    <string>4873</string>
                    <string>4875</string>
                    <string>4877</string>
                    <string>4879</string>
                    <string>4881</string>
                    <string>4883</string>
                    <string>4885</string>
                    <string>4887</string>
                    <string>4889</string>
                    <string>4891</string>
                    <string>4893</string>
                    <string>4895</string>
                    <string>5281</string>
                    <string>5285</string>
                    <string>5625</string>
                    <string>5627</string>
                    <string>5629</string>
                    <string>5631</string>
                    <string>5633</string>
                </array>
                <key>childLinkers</key>
                <array/>
            </dict>
            <dict>
                <key>id</key>
                <string>2999</string>
                <key>children</key>
                <array>
                    <string>3032</string>
                    <string>3035</string>
                    <string>3038</string>
                    <string>3054</string>
                    <string>4611</string>
                    <string>4613</string>
                    <string>4623</string>
                    <string>4625</string>
                    <string>4627</string>
                    <string>4644</string>
                    <string>4646</string>
                    <string>4648</string>
                    <string>4650</string>
                    <string>4653</string>
                    <string>4655</string>
                    <string>4657</string>
                </array>
                <key>childLinkers</key>
                <array/>
            </dict>
            <dict>
                <key>id</key>
                <string>3185</string>
                <key>children</key>
                <array>
                    <string>4912</string>
                    <string>4914</string>
                    <string>4916</string>
                    <string>4918</string>
                    <string>4920</string>
                    <string>4922</string>
                    <string>4924</string>
                    <string>4926</string>
                    <string>4928</string>
                    <string>4930</string>
                    <string>4932</string>
                    <string>4934</string>
                    <string>4936</string>
                    <string>4938</string>
                    <string>5291</string>
                    <string>5636</string>
                    <string>5638</string>
                    <string>5640</string>
                    <string>5642</string>
                    <string>5644</string>
                </array>
                <key>childLinkers</key>
                <array/>
            </dict>
            <dict>
                <key>id</key>
                <string>3117</string>
                <key>children</key>
                <array>
                    <string>3120</string>
                    <string>3122</string>
                    <string>3124</string>
                    <string>3126</string>
                    <string>3129</string>
                    <string>3132</string>
                    <string>3134</string>
                    <string>3136</string>
                    <string>3138</string>
                    <string>3140</string>
                    <string>5394</string>
                    <string>5396</string>
                    <string>5398</string>
                    <string>5400</string>
                    <string>5402</string>
                    <string>5520</string>
                    <string>5524</string>
                    <string>5528</string>
                </array>
                <key>childLinkers</key>
                <array>
                    <string>3141</string>
                    <string>3142</string>
                    <string>3143</string>
                    <string>3144</string>
                    <string>3145</string>
                    <string>3146</string>
                    <string>3147</string>
                    <string>3148</string>
                    <string>3149</string>
                </array>
            </dict>
            <dict>
                <key>id</key>
                <string>3186</string>
                <key>children</key>
                <array>
                    <string>5304</string>
                    <string>5326</string>
                    <string>5328</string>
                    <string>5330</string>
                    <string>5332</string>
                    <string>5334</string>
                    <string>5336</string>
                    <string>5338</string>
                    <string>5340</string>
                    <string>5342</string>
                    <string>5344</string>
                    <string>5346</string>
                    <string>5349</string>
                </array>
                <key>childLinkers</key>
                <array/>
            </dict>
            <dict>
                <key>id</key>
                <string>3150</string>
                <key>children</key>
                <array>
                    <string>3153</string>
                    <string>3155</string>
                    <string>3157</string>
                    <string>3159</string>
                    <string>3161</string>
                    <string>3163</string>
                    <string>3165</string>
                    <string>3167</string>
                    <string>3169</string>
                    <string>3171</string>
                    <string>4046</string>
                    <string>4048</string>
                    <string>4050</string>
                    <string>4052</string>
                    <string>4054</string>
                    <string>4056</string>
                    <string>4058</string>
                    <string>4060</string>
                    <string>5405</string>
                    <string>5407</string>
                    <string>5409</string>
                    <string>5411</string>
                </array>
                <key>childLinkers</key>
                <array/>
            </dict>
            <dict>
                <key>id</key>
                <string>3187</string>
                <key>children</key>
                <array>
                    <string>4990</string>
                    <string>4992</string>
                    <string>4994</string>
                    <string>4996</string>
                    <string>5002</string>
                    <string>5004</string>
                    <string>5006</string>
                    <string>5008</string>
                    <string>5010</string>
                    <string>5012</string>
                    <string>5369</string>
                    <string>5371</string>
                    <string>5647</string>
                    <string>5649</string>
                    <string>5651</string>
                    <string>5653</string>
                    <string>5655</string>
                </array>
                <key>childLinkers</key>
                <array/>
            </dict>
            <dict>
                <key>id</key>
                <string>3175</string>
                <key>children</key>
                <array>
                    <string>3280</string>
                    <string>3282</string>
                    <string>3284</string>
                    <string>3292</string>
                    <string>3294</string>
                    <string>3296</string>
                    <string>3298</string>
                    <string>4225</string>
                    <string>4227</string>
                    <string>4229</string>
                    <string>5414</string>
                    <string>5416</string>
                    <string>5418</string>
                    <string>5420</string>
                    <string>5422</string>
                    <string>5424</string>
                    <string>5534</string>
                    <string>5538</string>
                    <string>5542</string>
                </array>
                <key>childLinkers</key>
                <array/>
            </dict>
            <dict>
                <key>id</key>
                <string>3188</string>
                <key>children</key>
                <array>
                    <string>5030</string>
                    <string>5032</string>
                    <string>5034</string>
                    <string>5036</string>
                    <string>5038</string>
                    <string>5040</string>
                    <string>5042</string>
                    <string>5044</string>
                    <string>5046</string>
                    <string>5048</string>
                    <string>5050</string>
                    <string>5052</string>
                    <string>5363</string>
                    <string>5658</string>
                    <string>5660</string>
                    <string>5662</string>
                    <string>5664</string>
                    <string>5666</string>
                    <string>5668</string>
                    <string>5670</string>
                    <string>5672</string>
                </array>
                <key>childLinkers</key>
                <array/>
            </dict>
            <dict>
                <key>id</key>
                <string>3176</string>
                <key>children</key>
                <array>
                    <string>4176</string>
                    <string>4242</string>
                    <string>4244</string>
                    <string>4246</string>
                    <string>4248</string>
                    <string>4250</string>
                    <string>4252</string>
                    <string>4254</string>
                    <string>4256</string>
                    <string>4258</string>
                    <string>4260</string>
                    <string>5427</string>
                    <string>5429</string>
                    <string>5431</string>
                    <string>5433</string>
                    <string>5435</string>
                    <string>5437</string>
                    <string>5439</string>
                    <string>5548</string>
                    <string>5552</string>
                    <string>5556</string>
                </array>
                <key>childLinkers</key>
                <array/>
            </dict>
            <dict>
                <key>id</key>
                <string>3177</string>
                <key>children</key>
                <array>
                    <string>3322</string>
                    <string>3324</string>
                    <string>3326</string>
                    <string>3328</string>
                    <string>3330</string>
                    <string>3332</string>
                    <string>3334</string>
                    <string>3336</string>
                    <string>3338</string>
                    <string>3340</string>
                    <string>3963</string>
                    <string>3966</string>
                    <string>5442</string>
                    <string>5444</string>
                    <string>5562</string>
                    <string>5566</string>
                    <string>5570</string>
                </array>
                <key>childLinkers</key>
                <array>
                    <string>3952</string>
                    <string>3953</string>
                    <string>3954</string>
                    <string>3955</string>
                    <string>3956</string>
                    <string>3957</string>
                    <string>3958</string>
                    <string>3959</string>
                    <string>3960</string>
                </array>
            </dict>
            <dict>
                <key>id</key>
                <string>3178</string>
                <key>children</key>
                <array>
                    <string>3256</string>
                    <string>3258</string>
                    <string>3260</string>
                    <string>3262</string>
                    <string>3264</string>
                    <string>3266</string>
                    <string>3268</string>
                    <string>3270</string>
                    <string>3272</string>
                    <string>3274</string>
                    <string>4014</string>
                    <string>5447</string>
                    <string>5449</string>
                    <string>5451</string>
                    <string>5453</string>
                    <string>5455</string>
                    <string>5457</string>
                    <string>5459</string>
                    <string>5461</string>
                    <string>5576</string>
                    <string>5580</string>
                    <string>5584</string>
                </array>
                <key>childLinkers</key>
                <array>
                    <string>3997</string>
                    <string>3998</string>
                    <string>3999</string>
                    <string>4000</string>
                    <string>4001</string>
                    <string>4002</string>
                    <string>4003</string>
                    <string>4004</string>
                    <string>4005</string>
                </array>
            </dict>
        </array>
    </dict>
</plist>
